read_and_chat/__init__.py
read_and_chat/main.py
read_and_chat/main_cli.py
read_and_chat-0.0.1.dist-info/LICENSE
read_and_chat-0.0.1.dist-info/METADATA
read_and_chat-0.0.1.dist-info/WHEEL
read_and_chat-0.0.1.dist-info/entry_points.txt
read_and_chat-0.0.1.dist-info/top_level.txt
read_and_chat-0.0.1.dist-info/RECORD
