Metadata-Version: 2.1
Name: read-and-chat
Version: 0.0.1
Summary: Using text recognition for a ChatGPT prompt
Author: Timothy Niko, John Hoffer, Kevin Hill, Tyler Malka
Maintainer-email: John Hoffer <john@hoff.in>
License: MIT License
Project-URL: Repository, https://github.com/hssrobotics23/read-and-chat.git
Classifier: Development Status :: 2 - Pre-Alpha
Classifier: Programming Language :: Python
Requires-Python: >=3.8
License-File: LICENSE
